[
  {
    "rating": 5,
    "message": "Great is hands down the best freelancer I've ever worked with across any platform! His fullstack development skills are exceptional, but what truly sets him apart is how he consistently goes above and beyond expectations. He has an incredible talent for understanding exactly what you want and then delivering something even better than you imagined. Not only is he technically skilled, but his dedication to getting everything perfect is remarkable. He's the kind of developer who won't stop until everything is exactly right. I honestly wish I had more projects just to keep working with him. If you're looking for a top-tier fullstack developer who truly cares about your project, Great is your person. Cannot recommend him highly enough - he's simply outstanding!",
    "clientName": "Jordan Wong",
    "profilePicture": "/jordan-wong.jpg",
    "projectName": "ScoutSesh",
    "projectSlug": "scoutsesh"
  }
]
